{"_default": {"1": {"name": "Xhosa", "efficacy": 1.7483748666731311}, "2": {"name": "Blitz", "efficacy": 1.5197452811041203}, "3": {"name": "neo", "efficacy": 1.9935407591785936}, "4": {"name": "Pom Pom M4n.", "efficacy": 1.9527832552125424}, "5": {"name": "Point Blank", "efficacy": 1.4984786964071057}, "6": {"name": "r0B[i]n wOw~", "efficacy": 1.5304623287671233}, "7": {"name": "Adheera", "efficacy": 1.434907005579665}, "8": {"name": "Roman", "efficacy": 1.4453910913822132}, "9": {"name": "Hector", "efficacy": 1.4024658780709736}, "10": {"name": "Secret105v", "efficacy": 1.7278346690412585}, "11": {"name": "Glady", "efficacy": 1.3135507657402155}, "12": {"name": "alamaleste", "efficacy": 1.488122250872137}, "13": {"name": "LeThAl", "efficacy": 1.5088826387113272}, "14": {"name": "eXCALIBUr", "efficacy": 1.390846851800935}, "15": {"name": "CSK", "efficacy": 1.220177200236267}, "16": {"name": "Sparky", "efficacy": 1.4668291611769873}, "17": {"name": "NoFea[r]wOw", "efficacy": 1.8200915032679739}, "18": {"name": "<<OptimusPrime>>", "efficacy": 1.336510152284264}, "19": {"name": "BerLin", "efficacy": 1.2083439999999999}, "20": {"name": "Ethan", "efficacy": 1.170715396578538}, "21": {"name": "ZeR0_CoOL", "efficacy": 1.2675882352941177}, "22": {"name": "Skull_Crusher", "efficacy": 1.0422153846153845}, "23": {"name": "DEE", "efficacy": 1.7688265919102923}, "24": {"name": "MaxSteel", "efficacy": 1.2445640074211504}}}